celery_batches/__init__.py
celery_batches/trace.py
celery_batches-0.11.dist-info/licenses/LICENSE
celery_batches-0.11.dist-info/METADATA
celery_batches-0.11.dist-info/WHEEL
celery_batches-0.11.dist-info/top_level.txt
celery_batches-0.11.dist-info/RECORD
