Metadata-Version: 2.4
Name: celery-batches
Version: 0.11
Summary: Experimental task class that buffers messages and processes them as a list.
Author-email: Patrick Cloke <clokep@patrick.cloke.us>
License-Expression: BSD-3-Clause
Project-URL: Documentation, https://celery-batches.readthedocs.io
Project-URL: Changelog, https://github.com/clokep/celery-batches/blob/main/CHANGELOG.rst
Project-URL: Repository, https://github.com/clokep/celery-batches
Project-URL: Funding, https://github.com/sponsors/clokep
Project-URL: Issues, https://github.com/clokep/celery-batches/issues
Keywords: task,job,queue,distributed,messaging,actor,celery
Classifier: Development Status :: 3 - Alpha
Classifier: Topic :: System :: Distributed Computing
Classifier: Topic :: Software Development :: Object Brokering
Classifier: Programming Language :: Python
Classifier: Programming Language :: Python :: 3 :: Only
Classifier: Programming Language :: Python :: 3
Classifier: Programming Language :: Python :: 3.9
Classifier: Programming Language :: Python :: 3.10
Classifier: Programming Language :: Python :: 3.11
Classifier: Programming Language :: Python :: 3.12
Classifier: Programming Language :: Python :: 3.13
Classifier: Programming Language :: Python :: 3.14
Classifier: Programming Language :: Python :: Implementation :: CPython
Classifier: Programming Language :: Python :: Implementation :: PyPy
Classifier: Operating System :: OS Independent
Requires-Python: >=3.9
License-File: LICENSE
Requires-Dist: celery<5.7,>=5.0
Dynamic: license-file
